{
 "PrintNo":"K968","Session":2019,"Chamber":"ASSEMBLY","BillType":"Regular","Resolution":true,
 "Published":"2020-07-21T14:11:51.311065Z","Status":"ADOPTED","Milestones":[{"Type":"ADOPTED","Date":"2020-07-21"}],
 "Actions":[
  {"Text":"INTRODUCED","Date":"2020-07-21","Chamber":"ASSEMBLY"},
  {"Text":"ADOPTED","Date":"2020-07-21","Chamber":"ASSEMBLY"}
 ],
 "Sponsors":[{"ID":1249,"Name":"Marianne Buttenschon","Short":"BUTTENSCHON"}],
 "Title":"Commending Officer Jennifer Fassett upon the occasion of her retirement after more than 20 years of service to the Utica Police Department",
 "LawSection":"Resolutions, Legislative"
}