{
 "PrintNo":"K181","Session":2023,"Chamber":"ASSEMBLY","BillType":"Regular","Resolution":true,
 "Published":"2023-03-13T12:02:40.851992Z","Status":"ADOPTED","Milestones":[{"Type":"ADOPTED","Date":"2023-03-13"}],
 "Actions":[
  {"Text":"INTRODUCED","Date":"2023-03-13","Chamber":"ASSEMBLY"},
  {"Text":"ADOPTED","Date":"2023-03-13","Chamber":"ASSEMBLY"}
 ],
 "Sponsors":[{"ID":1524,"Name":"Edward Flood","Short":"FLOOD"}],
 "Title":"Congratulating Ward Melville High School upon the occasion of being named a 2022 National Blue Ribbon School by the United States Department of Education",
 "LawSection":"Resolutions, Legislative"
}