{
 "PrintNo":"A11360","Session":2025,"Chamber":"ASSEMBLY","BillType":"Assembly","Published":"2026-05-13T17:11:22.424201Z",
 "Status":"IN_ASSEMBLY_COMM","Committee":"Codes",
 "Milestones":[{"Type":"IN_ASSEMBLY_COMM","Date":"2026-05-18","Committee":"Codes"}],
 "Actions":[
  {"Text":"REFERRED TO CONSUMER AFFAIRS AND PROTECTION","Date":"2026-05-13","Chamber":"ASSEMBLY"},
  {"Text":"REPORTED REFERRED TO CODES","Date":"2026-05-18","Chamber":"ASSEMBLY"}
 ],
 "Sponsors":[{"ID":1530,"Name":"Grace Lee","Short":"LEE"}],
 "Title":"Requires the labeling of certain baby cosmetic products",
 "Summary":"Requires the labeling of certain baby cosmetic products if the cosmetic product contains a carcinogen.",
 "LawSection":"General Business Law","LawCode":"Add §399-aaaaaaa, Gen Bus L",
 "ActClause":"AN ACT to amend the general business law, in relation to the labeling of baby cosmetic products"
}