{
 "PrintNo":"A4712","Session":2025,"Chamber":"ASSEMBLY","BillType":"Assembly","Published":"2025-02-04T12:34:09.860991Z",
 "Status":"IN_ASSEMBLY_COMM","Committee":"Energy",
 "Milestones":[{"Type":"IN_ASSEMBLY_COMM","Date":"2025-02-04","Committee":"Energy"}],
 "Actions":[{"Text":"REFERRED TO ENERGY","Date":"2025-02-04","Chamber":"ASSEMBLY"}],
 "Sponsors":[
  {"ID":625,"Name":"Didi Barrett","Short":"BARRETT"},{"ID":906,"Name":"Rebecca Seawright","Short":"SEAWRIGHT"},
  {"ID":1564,"Name":"Paula Kay","Short":"KAY"},{"ID":1537,"Name":"Dana Levenberg","Short":"LEVENBERG"},
  {"ID":570,"Name":"William Magnarelli","Short":"MAGNARELLI"},{"ID":519,"Name":"Deborah Glick","Short":"GLICK"},
  {"ID":907,"Name":"Jo Anne Simon","Short":"SIMON"},{"ID":1144,"Name":"Harvey Epstein","Short":"EPSTEIN"}
 ],
 "Title":"Authorizes the secretary of state to appoint a person from the utility intervention unit within the consumer protection division to serve on the state energy planning board",
 "Summary":"Authorizes the secretary of state to appoint a person from the utility intervention unit within the consumer protection division to serve on the state energy planning board.",
 "LawSection":"Energy Law","LawCode":"Amd ยง6-102, Energy L",
 "ActClause":"AN ACT to amend the energy law, in relation to the composition of the state energy planning board",
 "SameAsPrintNo":"S2460-2025",
 "PreviousVersions":["S5290-2013","S4427-2015","S1978-2017","S2793-2019","S5861-2021","S3021-2023"]
}