{
 "PrintNo":"A6608","Session":2025,"Chamber":"ASSEMBLY","BillType":"Assembly","Published":"2025-03-06T15:06:52.363709Z",
 "Status":"IN_ASSEMBLY_COMM","Committee":"Transportation",
 "Milestones":[{"Type":"IN_ASSEMBLY_COMM","Date":"2026-01-07","Committee":"Transportation"}],
 "Actions":[
  {"Text":"REFERRED TO TRANSPORTATION","Date":"2025-03-06","Chamber":"ASSEMBLY"},
  {"Text":"REFERRED TO TRANSPORTATION","Date":"2026-01-07","Chamber":"ASSEMBLY"}
 ],
 "Sponsors":[{"ID":1553,"Name":"Tommy Schiavoni","Short":"SCHIAVONI"}],
 "Title":"Authorizes the village of North Haven to reduce the maximum speed limit along certain designated streets",
 "Summary":"Authorizes the village of North Haven, county of Suffolk, to reduce the maximum speed limit along certain designated streets in such village to not less than twenty miles per hour.",
 "LawSection":"Suffolk County",
 "ActClause":"AN ACT in relation to authorizing the village of North Haven, Suffolk county, to reduce the maximum speed limit along certain designated streets in such village to not less than 20 miles per hour",
 "SameAsPrintNo":"S5659-2025"
}