{
 "PrintNo":"A720","Session":2025,"Chamber":"ASSEMBLY","BillType":"Assembly","Published":"2025-01-06T14:30:39.220532Z",
 "Status":"IN_ASSEMBLY_COMM","Committee":"Codes",
 "Milestones":[{"Type":"IN_ASSEMBLY_COMM","Date":"2025-01-08","Committee":"Codes"}],
 "Actions":[{"Text":"REFERRED TO CODES","Date":"2025-01-08","Chamber":"ASSEMBLY"}],
 "Sponsors":[
  {"ID":1505,"Name":"Eddie Gibbs","Short":"GIBBS"},{"ID":1535,"Name":"MaryJane Shimsky","Short":"SHIMSKY"},
  {"ID":1474,"Name":"Phara Souffrant Forrest","Short":"FORREST"},{"ID":1141,"Name":"Al Taylor","Short":"TAYLOR"},
  {"ID":1144,"Name":"Harvey Epstein","Short":"EPSTEIN"},{"ID":484,"Name":"David Weprin","Short":"WEPRIN"}
 ],
 "Title":"Relates to conferring youthful offender status upon conviction of an eligible youth for a misdemeanor",
 "Summary":"Relates to conferring youthful offender status upon conviction of an eligible youth for a misdemeanor.",
 "LawSection":"Criminal Procedure Law","LawCode":"Amd ยง720.20, CP L",
 "ActClause":"AN ACT to amend the criminal procedure law, in relation to youthful offender determinations",
 "PreviousVersions":["A7212-2015","A2480-2017","A718-2019","A5752-2021","A9145-2023"]
}