{
 "PrintNo":"A7445","Session":2025,"Chamber":"ASSEMBLY","BillType":"Assembly","Published":"2025-03-28T13:46:45.157765Z",
 "Status":"IN_ASSEMBLY_COMM","Committee":"Housing",
 "Milestones":[{"Type":"IN_ASSEMBLY_COMM","Date":"2026-01-07","Committee":"Housing"}],
 "Actions":[
  {"Text":"REFERRED TO HOUSING","Date":"2025-03-28","Chamber":"ASSEMBLY"},
  {"Text":"REFERRED TO HOUSING","Date":"2026-01-07","Chamber":"ASSEMBLY"}
 ],
 "Sponsors":[
  {"ID":1527,"Name":"Michael Novakhov","Short":"NOVAKHOV"},
  {"ID":469,"Name":"Michael J. Fitzpatrick","Short":"FITZPATRICK"},{"ID":1152,"Name":"Chris Tague","Short":"TAGUE"},
  {"ID":1251,"Name":"Brian Manktelow","Short":"MANKTELOW"},{"ID":1556,"Name":"Daniel Norber","Short":"NORBER"}
 ],
 "Title":"Relates to community land mortgages and authorizes the state of New York mortgage agency to purchase community land mortgages from banks within the state",
 "Summary":"Relates to the purchase of community land mortgages; defines a community land mortgage as a mortgage that is secured by a first lien on a leasehold estate in real property that is improved by a residential structure wherein title to the real property is retained by a not-for-profit housing company or housing development fund company; authorizes the state of New York mortgage agency to purchase community land mortgages from banks within the state; ensures not-for-profit housing remains as affordable housing.",
 "LawSection":"Public Authorities Law","LawCode":"Amd ยง2402, add ยง2405-g, Pub Auth L",
 "ActClause":"AN ACT to amend the public authorities law, in relation to the purchase of community land mortgages",
 "PreviousVersions":["A6665-2007","A4522-2009","A2735-2011","A3213-2013","A3233-2015","A7670-2017","A6949-2019","A5597-2021","A4365-2023"]
}