{
 "PrintNo":"A9464","Session":2025,"Chamber":"ASSEMBLY","BillType":"Assembly","Published":"2026-01-06T17:41:47.66552Z",
 "Status":"IN_ASSEMBLY_COMM","Committee":"Labor",
 "Milestones":[{"Type":"IN_ASSEMBLY_COMM","Date":"2026-01-07","Committee":"Labor"}],
 "Actions":[
  {"Text":"REFERRED TO LABOR","Date":"2026-01-06","Chamber":"ASSEMBLY"},
  {"Text":"REFERRED TO LABOR","Date":"2026-01-07","Chamber":"ASSEMBLY"}
 ],
 "Sponsors":[{"ID":633,"Name":"Harry B. Bronson","Short":"BRONSON"}],
 "Title":"Relates to certain off-site custom fabrication public works projects and the payment of prevailing wage",
 "Summary":"Clarifies the definition of custom fabrication for the purposes of prevailing wage; requires certain reports for public works contracts including such custom fabrication.",
 "LawSection":"Labor Law","LawCode":"Amd ยง220, Lab L (as proposed in S.2536-A & A.2747-A)",
 "ActClause":"AN ACT to amend the labor law, in relation to certain off-site custom fabrication public works projects and the payment of prevailing wage",
 "PreviousVersions":["A8494-2021","A373-2023"]
}