{
 "PrintNo":"S10051","Session":2025,"Chamber":"SENATE","BillType":"Senate","Published":"2026-01-30T14:25:58.1521Z",
 "Status":"IN_SENATE_COMM","Committee":"Health",
 "Milestones":[{"Type":"IN_SENATE_COMM","Date":"2026-04-24","Committee":"Health"}],
 "Actions":[{"Text":"REFERRED TO HEALTH","Date":"2026-04-24","Chamber":"SENATE"}],
 "Sponsors":[{"ID":1572,"Name":"Sam Sutton","Short":"SUTTON"}],
 "Title":"Requires epinephrine auto-injector devices at children's overnight, summer day and traveling summer camps",
 "Summary":"Requires epinephrine devices at children's overnight, summer day and traveling summer day camps.",
 "LawSection":"Public Health Law","LawCode":"Amd §3000-c, add §1392-b, Pub Health L",
 "ActClause":"AN ACT to amend the public health law, in relation to requiring epinephrine devices at children's overnight, summer day and traveling summer camps",
 "PreviousVersions":["S5159-2013","S50-2015","S264-2017","S1480-2019","S443-2021","S2555-2023","S3858-2025"]
}