{
 "PrintNo":"S1380","Session":2025,"Chamber":"SENATE","BillType":"Senate","Published":"2025-01-09T13:16:10.207055Z",
 "Status":"SENATE_FLOOR",
 "Milestones":[
  {"Type":"IN_SENATE_COMM","Date":"2025-01-09","Committee":"Cultural Affairs, Tourism, Parks And Recreation"},
  {"Type":"SENATE_FLOOR","Date":"2025-04-08"}
 ],
 "Actions":[
  {"Text":"REFERRED TO CULTURAL AFFAIRS, TOURISM, PARKS AND RECREATION","Date":"2025-01-09","Chamber":"SENATE"},
  {"Text":"1ST REPORT CAL.662","Date":"2025-04-08","Chamber":"SENATE"}
 ],
 "Votes":[
  {
   "VoteType":"COMMITTEE","Date":"2025-04-08","Chamber":"SENATE",
   "Committee":"Cultural Affairs, Tourism, Parks And Recreation",
   "Votes":[
    {"ID":1552,"Name":"April Baskin","Short":"BASKIN","Vote":"Aye"},
    {"ID":1501,"Name":"Jeremy Cooney","Short":"COONEY","Vote":"Aye"},
    {"ID":1497,"Name":"Michelle Hinchey","Short":"HINCHEY","Vote":"Aye"},
    {"ID":1512,"Name":"Jessica Scarcella-Spanton","Short":"SCARCELLA-SPANTON","Vote":"Aye"},
    {"ID":373,"Name":"José M. Serrano","Short":"SERRANO","Vote":"Aye"},
    {"ID":1103,"Name":"James Tedisco","Short":"TEDISCO","Vote":"Aye"},
    {"ID":951,"Name":"Pamela Helming","Short":"HELMING","Vote":"Aye"}
   ]
  }
 ],
 "Sponsors":[
  {"ID":373,"Name":"José M. Serrano","Short":"SERRANO"},{"ID":1230,"Name":"Robert Jackson","Short":"JACKSON"},
  {"ID":1515,"Name":"Lea Webb","Short":"WEBB"}
 ],
 "Title":"Relates to the cleaning of playground equipment after pesticide exposure",
 "Summary":"Requires the department of environmental conservation and the department of health to establish certain standards related to the cleaning of playground equipment after pesticide exposure.",
 "LawSection":"Parks, Recreation and Historic Preservation Law","LawCode":"Add §29.17, Pks & Rec L",
 "ActClause":"AN ACT to amend the parks, recreation and historic preservation law, in relation to the cleaning of playground equipment after pesticide exposure",
 "SameAsPrintNo":"A1649-2025","PreviousVersions":["S8477-2017","S3571-2019","S1422-2021","S805-2023"]
}