{
 "PrintNo":"S386","Session":2025,"Chamber":"SENATE","BillType":"Senate","Published":"2024-12-30T14:31:34.077605Z",
 "Status":"IN_SENATE_COMM","Committee":"Investigations And Government Operations",
 "Milestones":[{"Type":"IN_SENATE_COMM","Date":"2025-01-08","Committee":"Investigations And Government Operations"}],
 "Actions":[{"Text":"REFERRED TO INVESTIGATIONS AND GOVERNMENT OPERATIONS","Date":"2025-01-08","Chamber":"SENATE"}],
 "Sponsors":[{"ID":1491,"Name":"Sean Ryan","Short":"RYAN S"}],"Title":"Relates to small business savings accounts",
 "Summary":"Relates to small business savings accounts; provides tax incentives for contributions and distributions.",
 "LawSection":"Tax Law","LawCode":"Add §50, amd §§209 & 612, Tax L",
 "ActClause":"AN ACT to amend the tax law, in relation to establishing small business savings accounts",
 "SameAsPrintNo":"A2460-2025","PreviousVersions":["S4376-2015","S3557-2017","S3163-2019","S702-2021","S6697-2023"]
}