{
 "PrintNo":"S5296","Session":2025,"Chamber":"SENATE","BillType":"Senate","Published":"2025-02-20T14:16:42.041211Z",
 "Status":"IN_SENATE_COMM","Committee":"Mental Health",
 "Milestones":[{"Type":"IN_SENATE_COMM","Date":"2025-02-20","Committee":"Mental Health"}],
 "Actions":[{"Text":"REFERRED TO MENTAL HEALTH","Date":"2025-02-20","Chamber":"SENATE"}],
 "Sponsors":[
  {"ID":1142,"Name":"Luis R. Sepúlveda","Short":"SEPULVEDA"},{"ID":1233,"Name":"Pete Harckham","Short":"HARCKHAM"},
  {"ID":409,"Name":"Andrew J. Lanza","Short":"LANZA"},{"ID":1489,"Name":"Anthony H. Palumbo","Short":"PALUMBO"},
  {"ID":1232,"Name":"James Skoufis","Short":"SKOUFIS"}
 ],
 "Title":"Establishes Nicole's law, which provides for treatment of individuals with self-inflicted, life-threatening injuries",
 "Summary":"Establishes Nicole's law, which provides for intake and discharge procedures regarding individuals with self-inflicted, life-threatening injuries.",
 "LawSection":"Mental Hygiene Law","LawCode":"Add §9.61, Ment Hyg L",
 "ActClause":"AN ACT to amend the mental hygiene law, in relation to establishing Nicole's law",
 "PreviousVersions":["S6629-2019","S4957-2021","S4345-2023"]
}