{
 "PrintNo":"S8494","Version":"B","Session":2025,"Chamber":"SENATE","BillType":"Senate",
 "Published":"2025-09-03T09:45:30.793597Z","Status":"IN_SENATE_COMM","Committee":"Labor",
 "Milestones":[{"Type":"IN_SENATE_COMM","Date":"2026-03-12","Committee":"Labor"}],
 "Actions":[
  {"Text":"REFERRED TO RULES","Date":"2025-09-03","Chamber":"SENATE"},
  {"Text":"REFERRED TO LABOR","Date":"2026-01-07","Chamber":"SENATE"},
  {"Text":"AMEND AND RECOMMIT TO LABOR","Date":"2026-02-18","Chamber":"SENATE"},
  {"Text":"PRINT NUMBER 8494A","Date":"2026-02-18","Chamber":"SENATE","Version":"A"},
  {"Text":"AMEND AND RECOMMIT TO LABOR","Date":"2026-03-12","Chamber":"SENATE","Version":"A"},
  {"Text":"PRINT NUMBER 8494B","Date":"2026-03-12","Chamber":"SENATE","Version":"B"}
 ],
 "Sponsors":[
  {"ID":1225,"Name":"John Liu","Short":"LIU"},{"ID":1571,"Name":"Patricia Fahy","Short":"FAHY"},
  {"ID":1230,"Name":"Robert Jackson","Short":"JACKSON"},{"ID":1499,"Name":"Peter Oberacker","Short":"OBERACKER"},
  {"ID":1232,"Name":"James Skoufis","Short":"SKOUFIS"}
 ],
 "Title":"Provides for permitted leaves of absence for members of civil air patrol",
 "Summary":"Provides for permitted leaves of absence for members of the civil air patrol during emergencies for purposes of assisting with such emergencies.",
 "LawSection":"Labor Law","LawCode":"Amd §202-l, Lab L",
 "ActClause":"AN ACT to amend the labor law, in relation to permitted leaves of absence for members of civil air patrol",
 "SameAsPrintNo":"A9350-2025"
}