{
 "PrintNo":"S8655","Session":2025,"Chamber":"SENATE","BillType":"Senate","Published":"2026-01-07T10:08:11.6526Z",
 "Status":"IN_SENATE_COMM","Committee":"Cities 1",
 "Milestones":[{"Type":"IN_SENATE_COMM","Date":"2026-01-07","Committee":"Cities 1"}],
 "Actions":[{"Text":"REFERRED TO CITIES 1","Date":"2026-01-07","Chamber":"SENATE"}],
 "Sponsors":[{"ID":1504,"Name":"Cordell Cleare","Short":"CLEARE"}],
 "Title":"Authorizes the conveyance of certain property by the city of New York to The Allah Youth Center in Mecca Inc.",
 "Summary":"Authorizes the conveyance of certain property by the city of New York to The Allah Youth Center in Mecca Inc.",
 "LawSection":"New York City",
 "ActClause":"AN ACT in relation to authorizing the conveyance of certain property by the city of New York to The Allah Youth Center in Mecca Inc."
}