{
 "PrintNo":"J585","Session":2021,"Chamber":"SENATE","BillType":"Regular and Joint","Resolution":true,
 "Published":"2021-04-02T09:06:59.340208Z","Status":"ADOPTED","Milestones":[{"Type":"ADOPTED","Date":"2021-04-06"}],
 "Actions":[
  {"Text":"REFERRED TO FINANCE","Date":"2021-04-02","Chamber":"SENATE"},
  {"Text":"REPORTED TO CALENDAR FOR CONSIDERATION","Date":"2021-04-06","Chamber":"SENATE"},
  {"Text":"ADOPTED","Date":"2021-04-06","Chamber":"SENATE"}
 ],
 "Sponsors":[{"ID":416,"Name":"Kevin S. Parker","Short":"PARKER"}],
 "Title":"Mourning the death of Jesse B. Powell, prominent Mason, distinguished citizen and devoted member of his community",
 "LawSection":"Resolutions, Legislative"
}