{
 "PrintNo":"J814","Session":2021,"Chamber":"SENATE","BillType":"Regular and Joint","Resolution":true,
 "Published":"2021-05-13T13:06:16.329591Z","Status":"IN_SENATE_COMM","Committee":"Finance",
 "Actions":[{"Text":"REFERRED TO FINANCE","Date":"2021-05-13","Chamber":"SENATE"}],
 "Sponsors":[{"ID":432,"Name":"James Sanders Jr.","Short":"SANDERS"}],
 "Title":"Memorializing Governor Andrew M. Cuomo to proclaim November 1, 2021, as Lung Cancer Screening Awareness Day in the State of New York",
 "LawSection":"Resolutions, Legislative"
}