{
 "PrintNo":"A10389","Session":2019,"Chamber":"ASSEMBLY","BillType":"Assembly","Published":"2020-05-04T16:55:28.564357Z",
 "Status":"IN_ASSEMBLY_COMM","Committee":"Housing",
 "Milestones":[{"Type":"IN_ASSEMBLY_COMM","Date":"2020-05-04","Committee":"Housing"}],
 "Actions":[{"Text":"REFERRED TO HOUSING","Date":"2020-05-04","Chamber":"ASSEMBLY"}],
 "Sponsors":[{"ID":520,"Name":"Linda Rosenthal","Short":"ROSENTHAL L"}],
 "Title":"Suspends any rent increases for rent controlled tenants for a period of one year",
 "Summary":"Suspends any rent increases for rent controlled tenants for a period of one year.",
 "LawSection":"Real Property",
 "ActClause":"AN ACT in relation to suspending any rent increases for rent controlled tenants for a period of one year; and providing for the repeal of such provisions upon expiration thereof"
}