{
 "PrintNo":"A1686","Session":2019,"Chamber":"ASSEMBLY","BillType":"Assembly","Published":"2019-01-16T17:08:35.017355Z",
 "Status":"IN_ASSEMBLY_COMM","Committee":"Ways And Means",
 "Milestones":[{"Type":"IN_ASSEMBLY_COMM","Date":"2020-01-08","Committee":"Ways And Means"}],
 "Actions":[
  {"Text":"REFERRED TO EDUCATION","Date":"2019-01-16","Chamber":"ASSEMBLY"},
  {"Text":"REPORTED REFERRED TO WAYS AND MEANS","Date":"2019-06-05","Chamber":"ASSEMBLY"},
  {"Text":"REFERRED TO WAYS AND MEANS","Date":"2020-01-08","Chamber":"ASSEMBLY"}
 ],
 "Votes":[
  {
   "VoteType":"Favorable refer to committee Ways and Means","Date":"1969-12-31","Chamber":"ASSEMBLY",
   "Votes":[
    {"ID":534,"Short":"BENEDETTO","Vote":"Aye"},{"ID":1127,"Short":"WALSH","Vote":"Aye"},
    {"ID":466,"Short":"ENGLEBRIGHT","Vote":"Aye"},{"ID":608,"Short":"RA","Vote":"Aye"},
    {"ID":536,"Short":"ARROYO","Vote":"Aye"},{"ID":480,"Short":"MCDONOUGH","Vote":"Aye"},
    {"ID":570,"Short":"MAGNARELLI","Vote":"Aye"},{"ID":909,"Short":"LAWRENCE","Vote":"Aye"},
    {"ID":540,"Short":"PAULIN","Vote":"Aye"},{"ID":1125,"Short":"MILLER","Vote":"Aye"},
    {"ID":468,"Short":"RAMOS","Vote":"Aye"},{"ID":1150,"Short":"MIKULIN","Vote":"Aye"},
    {"ID":522,"Short":"O'DONNELL","Vote":"Aye"},{"ID":615,"Short":"MALLIOTAKIS","Vote":"Aye"},
    {"ID":456,"Short":"TITUS","Vote":"Aye"},{"ID":575,"Short":"LIFTON","Vote":"Aye"},
    {"ID":638,"Short":"RYAN","Vote":"Aye"},{"ID":663,"Short":"MOSLEY","Vote":"Aye"},
    {"ID":665,"Short":"OTIS","Vote":"Aye"},{"ID":906,"Short":"SEAWRIGHT","Vote":"Aye"},
    {"ID":1089,"Short":"HYNDMAN","Vote":"Aye"},{"ID":633,"Short":"BRONSON","Vote":"Aye"},
    {"ID":907,"Short":"SIMON","Vote":"Aye"},{"ID":1130,"Short":"D'URSO","Vote":"Aye"},
    {"ID":1141,"Short":"TAYLOR","Vote":"Aye"},{"ID":1128,"Short":"DICKENS","Vote":"Aye"},
    {"ID":902,"Short":"JOYNER","Vote":"Aye"},{"ID":546,"Short":"JAFFEE","Vote":"Nay"},
    {"ID":901,"Short":"JEAN-PIERRE","Vote":"Nay"},{"ID":659,"Short":"KIM","Vote":"Excused"},
    {"ID":656,"Short":"DIPIETRO","Vote":"Absent"}
   ]
  }
 ],
 "Sponsors":[
  {"ID":1131,"Name":"Stacey Pheffer Amato","Short":"PHEFFER AMATO"},
  {"ID":1122,"Name":"Robert C. Carroll","Short":"CARROLL"},{"ID":1139,"Name":"Daniel Rosenthal","Short":"ROSENTHAL D"},
  {"ID":498,"Name":"Steven Cymbrowitz","Short":"CYMBROWITZ"},{"ID":484,"Name":"David Weprin","Short":"WEPRIN"},
  {"ID":618,"Name":"Dan Quart","Short":"QUART"},{"ID":898,"Name":"Rodneyse Bichotte Hermelyn","Short":"BICHOTTE"},
  {"ID":516,"Name":"Michael Cusick","Short":"CUSICK"},{"ID":612,"Name":"Aravella Simotas","Short":"SIMOTAS"},
  {"ID":503,"Name":"Joseph Lentol","Short":"LENTOL"},{"ID":912,"Name":"Diana Richardson","Short":"RICHARDSON"},
  {"ID":1243,"Name":"Simcha Eichenstein","Short":"EICHENSTEIN"},{"ID":1130,"Name":"Anthony D'Urso","Short":"D'URSO"},
  {"ID":907,"Name":"Jo Anne Simon","Short":"SIMON"}
 ],
 "Title":"Relates to providing transportation for children with a handicapping condition",
 "Summary":"Relates to providing transportation for children with handicapping conditions; removes the requirement that a child attends the school the district is providing transportation to for the purpose of receiving services or programs similar to special educational programs recommended for such child by the local committee on special education.",
 "LawSection":"Education Law","LawCode":"Amd ยง4402, Ed L",
 "ActClause":"AN ACT to amend the education law, in relation to providing transportation for children with handicapping conditions",
 "SameAsPrintNo":"S4168-2019","PreviousVersions":["A9648-2017"]
}