{
 "PrintNo":"A5424","Session":2019,"Chamber":"ASSEMBLY","BillType":"Assembly","Published":"2019-02-12T10:32:47.358299Z",
 "Status":"ASSEMBLY_FLOOR",
 "Milestones":[
  {"Type":"IN_ASSEMBLY_COMM","Date":"2019-02-12","Committee":"Judiciary"},{"Type":"ASSEMBLY_FLOOR","Date":"2019-05-30"}
 ],
 "Actions":[
  {"Text":"REFERRED TO JUDICIARY","Date":"2019-02-12","Chamber":"ASSEMBLY"},
  {"Text":"REPORTED","Date":"2019-05-30","Chamber":"ASSEMBLY"},
  {"Text":"ADVANCED TO THIRD READING CAL.518","Date":"2019-05-30","Chamber":"ASSEMBLY"},
  {"Text":"SUBSTITUTED BY S748","Date":"2019-06-04","Chamber":"ASSEMBLY"}
 ],
 "Votes":[
  {
   "VoteType":"Favorable","Date":"1969-12-31","Chamber":"ASSEMBLY",
   "Votes":[
    {"ID":533,"Short":"DINOWITZ","Vote":"Aye"},{"ID":666,"Short":"PALUMBO","Vote":"Aye"},
    {"ID":456,"Short":"TITUS","Vote":"Aye"},{"ID":474,"Short":"LAVINE","Vote":"Aye"},
    {"ID":642,"Short":"GOODELL","Vote":"Aye"},{"ID":545,"Short":"ZEBROWSKI","Vote":"Aye"},
    {"ID":1126,"Short":"NORRIS","Vote":"Aye"},{"ID":484,"Short":"WEPRIN","Vote":"Aye"},
    {"ID":1127,"Short":"WALSH","Vote":"Aye"},{"ID":610,"Short":"BRAUNSTEIN","Vote":"Aye"},
    {"ID":1252,"Short":"BYRNES","Vote":"Aye"},{"ID":612,"Short":"SIMOTAS","Vote":"Aye"},
    {"ID":618,"Short":"QUART","Vote":"Aye"},{"ID":654,"Short":"BUCHWALD","Vote":"Aye"},
    {"ID":675,"Short":"STECK","Vote":"Aye"},{"ID":906,"Short":"SEAWRIGHT","Vote":"Aye"},
    {"ID":902,"Short":"JOYNER","Vote":"Aye"},{"ID":622,"Short":"ABINANTI","Vote":"Aye"},
    {"ID":1134,"Short":"WRIGHT","Vote":"Aye"},{"ID":1133,"Short":"WALLACE","Vote":"Aye"},
    {"ID":476,"Short":"MONTESANO","Vote":"Excused"}
   ]
  }
 ],
 "Sponsors":[
  {"ID":537,"Name":"Marcos Crespo","Short":"CRESPO"},{"ID":625,"Name":"Didi Barrett","Short":"BARRETT"},
  {"ID":899,"Name":"Michael Blake","Short":"BLAKE"},{"ID":610,"Name":"Edward Braunstein","Short":"BRAUNSTEIN"},
  {"ID":655,"Name":"Maritza Davila","Short":"DAVILA"},{"ID":488,"Name":"Andrew Hevesi","Short":"HEVESI"},
  {"ID":1089,"Name":"Alicia Hyndman","Short":"HYNDMAN"},{"ID":546,"Name":"Ellen C. Jaffee","Short":"JAFFEE"},
  {"ID":901,"Name":"Kimberly Jean-Pierre","Short":"JEAN-PIERRE"},{"ID":902,"Name":"Latoya Joyner","Short":"JOYNER"},
  {"ID":462,"Name":"Andrew Raia","Short":"RAIA"},{"ID":907,"Name":"Jo Anne Simon","Short":"SIMON"},
  {"ID":612,"Name":"Aravella Simotas","Short":"SIMOTAS"},{"ID":675,"Name":"Phil Steck","Short":"STECK"},
  {"ID":673,"Name":"Michaelle C. Solages","Short":"SOLAGES"},{"ID":1130,"Name":"Anthony D'Urso","Short":"D'URSO"},
  {"ID":667,"Name":"Victor M. Pichardo","Short":"PICHARDO"},{"ID":906,"Name":"Rebecca Seawright","Short":"SEAWRIGHT"},
  {"ID":1240,"Name":"Taylor Darling","Short":"DARLING"},{"ID":1257,"Name":"Karines Reyes","Short":"REYES"},
  {"ID":520,"Name":"Linda Rosenthal","Short":"ROSENTHAL L"}
 ],
 "Title":"Provides an exemption from jury duty for breastfeeding women",
 "Summary":"Provides an exemption from jury duty for breastfeeding women; allows that such breastfeeding mother's jury duty shall be postponed up to two years after the date on which such service otherwise is to commence.",
 "LawSection":"Judiciary Law","LawCode":"Amd ยง517, Judy L",
 "ActClause":"AN ACT to amend the judiciary law, in relation to providing an exemption from jury duty for breastfeeding women",
 "SameAsPrintNo":"S748-2019","PreviousVersions":["A6793-2015","A6111-2017"]
}