{
 "PrintNo":"A5540","Session":2019,"Chamber":"ASSEMBLY","BillType":"Assembly","Published":"2019-02-13T12:13:40.185273Z",
 "Status":"IN_ASSEMBLY_COMM","Committee":"Social Services",
 "Milestones":[{"Type":"IN_ASSEMBLY_COMM","Date":"2020-01-08","Committee":"Social Services"}],
 "Actions":[
  {"Text":"REFERRED TO SOCIAL SERVICES","Date":"2019-02-13","Chamber":"ASSEMBLY"},
  {"Text":"REFERRED TO SOCIAL SERVICES","Date":"2020-01-08","Chamber":"ASSEMBLY"},
  {"Text":"HELD FOR CONSIDERATION IN SOCIAL SERVICES","Date":"2020-07-15","Chamber":"ASSEMBLY"}
 ],
 "Votes":[
  {
   "VoteType":"Held for Consideration","Date":"1969-12-31","Chamber":"ASSEMBLY",
   "Votes":[
    {"ID":488,"Short":"HEVESI","Vote":"Aye"},{"ID":460,"Short":"AUBRY","Vote":"Aye"},
    {"ID":659,"Short":"KIM","Vote":"Aye"},{"ID":673,"Short":"SOLAGES","Vote":"Aye"},
    {"ID":667,"Short":"PICHARDO","Vote":"Aye"},{"ID":655,"Short":"DAVILA","Vote":"Aye"},
    {"ID":493,"Short":"BARRON","Vote":"Aye"},{"ID":1105,"Short":"HUNTER","Vote":"Aye"},
    {"ID":520,"Short":"ROSENTHAL","Vote":"Aye"},{"ID":1146,"Short":"FERNANDEZ","Vote":"Aye"},
    {"ID":1243,"Short":"EICHENSTEIN","Vote":"Aye"},{"ID":1257,"Short":"REYES","Vote":"Aye"},
    {"ID":1247,"Short":"WALCZYK","Vote":"Nay"},{"ID":642,"Short":"GOODELL","Vote":"Nay"},
    {"ID":674,"Short":"STEC","Vote":"Nay"},{"ID":1239,"Short":"LIPETRI","Vote":"Nay"},
    {"ID":1250,"Short":"SALKA","Vote":"Nay"}
   ]
  }
 ],
 "Sponsors":[
  {"ID":642,"Name":"Andrew Goodell","Short":"GOODELL"},{"ID":574,"Name":"William A. Barclay","Short":"BARCLAY"},
  {"ID":599,"Name":"Joseph Giglio","Short":"GIGLIO"},{"ID":1125,"Name":"Brian D. Miller","Short":"MILLER B"},
  {"ID":462,"Name":"Andrew Raia","Short":"RAIA"},{"ID":1135,"Name":"Angelo J. Morinello","Short":"MORINELLO"},
  {"ID":636,"Name":"Christopher Friend","Short":"FRIEND"}
 ],
 "Title":"Relates to certain educational requirements for public assistance",
 "Summary":"Relates to requiring participation in education programs leading to a high school diploma or high school equivalency diploma for those seeking public assistance.",
 "LawSection":"Social Services Law","LawCode":"Amd ยง131, Soc Serv L",
 "ActClause":"AN ACT to amend the social services law, in relation to requiring participation in educational programs leading to a high school diploma or high school equivalency diploma for those seeking public assistance",
 "PreviousVersions":["A9185-2013","A5110-2015","A4357-2017"]
}