{
 "PrintNo":"A6957","Session":2019,"Chamber":"ASSEMBLY","BillType":"Assembly","Published":"2019-03-27T10:10:36.203463Z",
 "Status":"IN_ASSEMBLY_COMM","Committee":"Codes",
 "Milestones":[{"Type":"IN_ASSEMBLY_COMM","Date":"2020-01-08","Committee":"Codes"}],
 "Actions":[
  {"Text":"REFERRED TO CODES","Date":"2019-03-27","Chamber":"ASSEMBLY"},
  {"Text":"REFERRED TO CODES","Date":"2020-01-08","Chamber":"ASSEMBLY"}
 ],
 "Sponsors":[{"ID":503,"Name":"Joseph Lentol","Short":"LENTOL"}],
 "Title":"Enacts the uniform collateral consequences of conviction act",
 "Summary":"Enacts the uniform collateral consequences of conviction act requiring the division of criminal justice services to collect and publish laws regarding collateral consequences of conviction and requiring notification to convicts of collateral consequences of such convictions.",
 "LawSection":"Criminal Procedure Law","LawCode":"Add Art 435 §§435.00 - 435.70, CP L",
 "ActClause":"AN ACT to amend the criminal procedure law, in relation to collateral consequences of convictions",
 "PreviousVersions":["A8546-2011","A3799-2013","A2925-2015","A3063-2017"]
}