{
 "PrintNo":"A7104","Version":"A","Session":2019,"Chamber":"ASSEMBLY","BillType":"Assembly",
 "Published":"2019-04-08T14:19:42.713007Z","Status":"ASSEMBLY_FLOOR",
 "Milestones":[{"Type":"IN_ASSEMBLY_COMM","Date":"2020-07-14","Committee":"Rules"},{"Type":"ASSEMBLY_FLOOR","Date":"2020-07-20"}],
 "Actions":[
  {"Text":"REFERRED TO EDUCATION","Date":"2019-04-08","Chamber":"ASSEMBLY"},
  {"Text":"REFERRED TO EDUCATION","Date":"2020-01-08","Chamber":"ASSEMBLY"},
  {"Text":"AMEND (T) AND RECOMMIT TO EDUCATION","Date":"2020-02-26","Chamber":"ASSEMBLY"},
  {"Text":"PRINT NUMBER 7104A","Date":"2020-02-26","Chamber":"ASSEMBLY","Version":"A"},
  {"Text":"REPORTED REFERRED TO RULES","Date":"2020-07-14","Chamber":"ASSEMBLY","Version":"A"},
  {"Text":"REPORTED","Date":"2020-07-20","Chamber":"ASSEMBLY","Version":"A"},
  {"Text":"RULES REPORT CAL.169","Date":"2020-07-20","Chamber":"ASSEMBLY","Version":"A"},
  {"Text":"SUBSTITUTED BY S3873A","Date":"2020-07-20","Chamber":"ASSEMBLY","Version":"A"}
 ],
 "Votes":[
  {
   "VoteType":"Favorable refer to committee Rules","Date":"1969-12-31","Chamber":"ASSEMBLY",
   "Votes":[
    {"ID":534,"Short":"BENEDETTO","Vote":"Aye"},{"ID":1127,"Short":"WALSH","Vote":"Aye"},
    {"ID":466,"Short":"ENGLEBRIGHT","Vote":"Aye"},{"ID":536,"Short":"ARROYO","Vote":"Aye"},
    {"ID":909,"Short":"LAWRENCE","Vote":"Aye"},{"ID":570,"Short":"MAGNARELLI","Vote":"Aye"},
    {"ID":1125,"Short":"MILLER","Vote":"Aye"},{"ID":540,"Short":"PAULIN","Vote":"Aye"},
    {"ID":1150,"Short":"MIKULIN","Vote":"Aye"},{"ID":468,"Short":"RAMOS","Vote":"Aye"},
    {"ID":615,"Short":"MALLIOTAKIS","Vote":"Aye"},{"ID":522,"Short":"O'DONNELL","Vote":"Aye"},
    {"ID":575,"Short":"LIFTON","Vote":"Aye"},{"ID":579,"Short":"KOLB","Vote":"Aye"},
    {"ID":659,"Short":"KIM","Vote":"Aye"},{"ID":638,"Short":"RYAN","Vote":"Aye"},
    {"ID":663,"Short":"MOSLEY","Vote":"Aye"},{"ID":665,"Short":"OTIS","Vote":"Aye"},
    {"ID":906,"Short":"SEAWRIGHT","Vote":"Aye"},{"ID":546,"Short":"JAFFEE","Vote":"Aye"},
    {"ID":1089,"Short":"HYNDMAN","Vote":"Aye"},{"ID":633,"Short":"BRONSON","Vote":"Aye"},
    {"ID":907,"Short":"SIMON","Vote":"Aye"},{"ID":901,"Short":"JEAN-PIERRE","Vote":"Aye"},
    {"ID":1130,"Short":"D'URSO","Vote":"Aye"},{"ID":1141,"Short":"TAYLOR","Vote":"Aye"},
    {"ID":1128,"Short":"DICKENS","Vote":"Aye"},{"ID":902,"Short":"JOYNER","Vote":"Aye"},
    {"ID":898,"Short":"BICHOTTE","Vote":"Aye"},{"ID":480,"Short":"MCDONOUGH","Vote":"Excused"},
    {"ID":656,"Short":"DIPIETRO","Vote":"Excused"}
   ]
  },
  {
   "VoteType":"Favorable","Date":"1969-12-31","Chamber":"ASSEMBLY","Committee":"RULES",
   "Votes":[
    {"ID":534,"Short":"BENEDETTO","Vote":"Aye"},{"ID":1127,"Short":"WALSH","Vote":"Aye"},
    {"ID":466,"Short":"ENGLEBRIGHT","Vote":"Aye"},{"ID":536,"Short":"ARROYO","Vote":"Aye"},
    {"ID":909,"Short":"LAWRENCE","Vote":"Aye"},{"ID":570,"Short":"MAGNARELLI","Vote":"Aye"},
    {"ID":1125,"Short":"MILLER","Vote":"Aye"},{"ID":540,"Short":"PAULIN","Vote":"Aye"},
    {"ID":1150,"Short":"MIKULIN","Vote":"Aye"},{"ID":468,"Short":"RAMOS","Vote":"Aye"},
    {"ID":615,"Short":"MALLIOTAKIS","Vote":"Aye"},{"ID":522,"Short":"O'DONNELL","Vote":"Aye"},
    {"ID":575,"Short":"LIFTON","Vote":"Aye"},{"ID":579,"Short":"KOLB","Vote":"Aye"},
    {"ID":659,"Short":"KIM","Vote":"Aye"},{"ID":638,"Short":"RYAN","Vote":"Aye"},
    {"ID":663,"Short":"MOSLEY","Vote":"Aye"},{"ID":665,"Short":"OTIS","Vote":"Aye"},
    {"ID":906,"Short":"SEAWRIGHT","Vote":"Aye"},{"ID":546,"Short":"JAFFEE","Vote":"Aye"},
    {"ID":1089,"Short":"HYNDMAN","Vote":"Aye"},{"ID":633,"Short":"BRONSON","Vote":"Aye"},
    {"ID":907,"Short":"SIMON","Vote":"Aye"},{"ID":901,"Short":"JEAN-PIERRE","Vote":"Aye"},
    {"ID":1130,"Short":"D'URSO","Vote":"Aye"},{"ID":1141,"Short":"TAYLOR","Vote":"Aye"},
    {"ID":1128,"Short":"DICKENS","Vote":"Aye"},{"ID":902,"Short":"JOYNER","Vote":"Aye"},
    {"ID":898,"Short":"BICHOTTE","Vote":"Aye"},{"ID":574,"Short":"BARCLAY","Vote":"Aye"},
    {"ID":527,"Short":"GOTTFRIED","Vote":"Aye"},{"ID":557,"Short":"CROUCH","Vote":"Aye"},
    {"ID":503,"Short":"LENTOL","Vote":"Aye"},{"ID":491,"Short":"NOLAN","Vote":"Aye"},
    {"ID":589,"Short":"HAWLEY","Vote":"Aye"},{"ID":494,"Short":"WEINSTEIN","Vote":"Aye"},
    {"ID":599,"Short":"GIGLIO","Vote":"Aye"},{"ID":504,"Short":"ORTIZ","Vote":"Aye"},
    {"ID":615,"Short":"MALLIOTAKIS","Vote":"Aye"},{"ID":539,"Short":"PRETLOW","Vote":"Aye"},
    {"ID":631,"Short":"BLANKENBUSH","Vote":"Aye"},{"ID":457,"Short":"COOK","Vote":"Aye"},
    {"ID":1126,"Short":"NORRIS","Vote":"Aye"},{"ID":460,"Short":"AUBRY","Vote":"Aye"},
    {"ID":466,"Short":"ENGLEBRIGHT","Vote":"Aye"},{"ID":533,"Short":"DINOWITZ","Vote":"Aye"},
    {"ID":500,"Short":"COLTON","Vote":"Aye"},{"ID":570,"Short":"MAGNARELLI","Vote":"Aye"},
    {"ID":511,"Short":"PERRY","Vote":"Aye"},{"ID":540,"Short":"PAULIN","Vote":"Aye"},
    {"ID":591,"Short":"PEOPLES-STOKES","Vote":"Aye"},{"ID":534,"Short":"BENEDETTO","Vote":"Aye"},
    {"ID":474,"Short":"LAVINE","Vote":"Aye"},{"ID":576,"Short":"LUPARDO","Vote":"Aye"},
    {"ID":545,"Short":"ZEBROWSKI","Vote":"Aye"},{"ID":464,"Short":"THIELE","Vote":"Aye"},
    {"ID":480,"Short":"MCDONOUGH","Vote":"Excused"},{"ID":656,"Short":"DIPIETRO","Vote":"Excused"},
    {"ID":535,"Short":"HEASTIE","Vote":"Excused"},{"ID":573,"Short":"FINCH","Vote":"Excused"},
    {"ID":519,"Short":"GLICK","Vote":"Excused"}
   ]
  }
 ],
 "Sponsors":[
  {"ID":1249,"Name":"Marianne Buttenschon","Short":"BUTTENSCHON"},{"ID":1144,"Name":"Harvey Epstein","Short":"EPSTEIN"},
  {"ID":621,"Name":"Sandy Galef","Short":"GALEF"},{"ID":464,"Name":"Fred Thiele","Short":"THIELE"},
  {"ID":576,"Name":"Donna Lupardo","Short":"LUPARDO"},{"ID":886,"Name":"Carrie Woerner","Short":"WOERNER"},
  {"ID":662,"Name":"John T. McDonald III","Short":"MCDONALD"},{"ID":1130,"Name":"Anthony D'Urso","Short":"D'URSO"},
  {"ID":527,"Name":"Richard Gottfried","Short":"GOTTFRIED R"},{"ID":669,"Name":"Nily Rozic","Short":"ROZIC"},
  {"ID":901,"Name":"Kimberly Jean-Pierre","Short":"JEAN-PIERRE"},{"ID":1258,"Name":"Nader Sayegh","Short":"SAYEGH"},
  {"ID":665,"Name":"Steven Otis","Short":"OTIS"},{"ID":1120,"Name":"Billy Jones","Short":"JONES"},
  {"ID":457,"Name":"Vivian Cook","Short":"COOK"},{"ID":520,"Name":"Linda Rosenthal","Short":"ROSENTHAL L"},
  {"ID":667,"Name":"Victor M. Pichardo","Short":"PICHARDO"},{"ID":1119,"Name":"Brian Barnwell","Short":"BARNWELL"}
 ],
 "Title":"Authorizes and directs boards of cooperative educational services to establish an agriculture program for students",
 "Summary":"Authorizes and directs boards of cooperative educational services to establish an agriculture program for students.",
 "LawSection":"Education Law","LawCode":"Amd ยง1950, Ed L",
 "ActClause":"AN ACT to amend the education law, in relation to authorizing and directing boards of cooperative educational services to establish an agriculture program for students",
 "SameAsPrintNo":"S3873-2019","PreviousVersions":["A9289-2013","A2410-2015","A4385-2017"]
}