{
 "PrintNo":"K413","Session":2019,"Chamber":"ASSEMBLY","BillType":"Regular","Resolution":true,
 "Published":"2019-05-15T09:48:44.847349Z","Status":"ADOPTED","Milestones":[{"Type":"ADOPTED","Date":"2019-05-15"}],
 "Actions":[
  {"Text":"INTRODUCED","Date":"2019-05-15","Chamber":"ASSEMBLY"},
  {"Text":"ADOPTED","Date":"2019-05-15","Chamber":"ASSEMBLY"}
 ],
 "Sponsors":[
  {"ID":631,"Name":"Kenneth Blankenbush","Short":"BLANKENBUSH"},{"ID":1248,"Name":"Robert Smullen","Short":"SMULLEN"},
  {"ID":1247,"Name":"Mark Walczyk","Short":"WALCZYK"}
 ],
 "Title":"Mourning the death of Mary Lou Rupp, St. Lawrence County Clerk, distinguished citizen and devoted member of her community",
 "LawSection":"Resolutions, Legislative"
}