{
 "PrintNo":"K510","Session":2019,"Chamber":"ASSEMBLY","BillType":"Regular","Resolution":true,
 "Published":"2019-06-05T16:19:46.685834Z","Status":"ADOPTED","Milestones":[{"Type":"ADOPTED","Date":"2019-06-06"}],
 "Actions":[
  {"Text":"REFERRED TO CALENDAR","Date":"2019-06-05","Chamber":"ASSEMBLY"},
  {"Text":"ADOPTED","Date":"2019-06-06","Chamber":"ASSEMBLY"}
 ],
 "Sponsors":[
  {"ID":633,"Name":"Harry B. Bronson","Short":"BRONSON"},{"ID":493,"Name":"Charles Barron","Short":"BARRON"},
  {"ID":908,"Name":"Karl Brabenec","Short":"BRABENEC"},{"ID":610,"Name":"Edward Braunstein","Short":"BRAUNSTEIN"},
  {"ID":498,"Name":"Steven Cymbrowitz","Short":"CYMBROWITZ"},{"ID":533,"Name":"Jeffrey Dinowitz","Short":"DINOWITZ"},
  {"ID":488,"Name":"Andrew Hevesi","Short":"HEVESI"},{"ID":1259,"Name":"Jonathan Jacobson","Short":"JACOBSON"},
  {"ID":576,"Name":"Donna Lupardo","Short":"LUPARDO"},{"ID":1135,"Name":"Angelo J. Morinello","Short":"MORINELLO"},
  {"ID":1126,"Name":"Michael J. Norris","Short":"NORRIS"},{"ID":504,"Name":"Felix Ortiz","Short":"ORTIZ"},
  {"ID":907,"Name":"Jo Anne Simon","Short":"SIMON"},{"ID":612,"Name":"Aravella Simotas","Short":"SIMOTAS"},
  {"ID":675,"Name":"Phil Steck","Short":"STECK"},{"ID":464,"Name":"Fred Thiele","Short":"THIELE"},
  {"ID":494,"Name":"Helene Weinstein","Short":"WEINSTEIN"},{"ID":545,"Name":"Kenneth Zebrowski","Short":"ZEBROWSKI"}
 ],
 "Title":"Memorializing Governor Andrew M. Cuomo to proclaim October 2019, as Breast Cancer Awareness Month in the State of New York",
 "LawSection":"Resolutions, Legislative"
}