{
 "PrintNo":"S3578","Session":2019,"Chamber":"SENATE","BillType":"Senate","Published":"2019-02-11T09:50:48.389656Z",
 "Status":"IN_SENATE_COMM","Committee":"Energy And Telecommunications",
 "Milestones":[{"Type":"IN_SENATE_COMM","Date":"2020-01-08","Committee":"Energy And Telecommunications"}],
 "Actions":[
  {"Text":"REFERRED TO ENERGY AND TELECOMMUNICATIONS","Date":"2019-02-11","Chamber":"SENATE"},
  {"Text":"REFERRED TO ENERGY AND TELECOMMUNICATIONS","Date":"2020-01-08","Chamber":"SENATE"}
 ],
 "Sponsors":[
  {"ID":416,"Name":"Kevin S. Parker","Short":"PARKER"},{"ID":1102,"Name":"Jamaal Bailey","Short":"BAILEY"},
  {"ID":381,"Name":"Velmanette Montgomery","Short":"MONTGOMERY"}
 ],
 "Title":"Authorizes virtual net energy metering",
 "Summary":"Authorizes virtual net energy metering; provides for the ownership and operation of energy generating equipment by municipalities and groups of farmers and businesses for their joint benefit; provides for the net energy metering of the electricity used by the members of such entities.",
 "LawSection":"Public Service Law","LawCode":"Add ยง66-p, Pub Serv L",
 "ActClause":"AN ACT to amend the public service law, in relation to authorizing virtual net energy metering",
 "PreviousVersions":["S3625-2011","S3217-2013","S2792-2015","S3893-2017"]
}