{
 "PrintNo":"S4501","Session":2019,"Chamber":"SENATE","BillType":"Senate","Published":"2019-03-13T14:05:53.740364Z",
 "Status":"IN_SENATE_COMM","Committee":"Judiciary",
 "Milestones":[{"Type":"IN_SENATE_COMM","Date":"2020-01-08","Committee":"Judiciary"}],
 "Actions":[
  {"Text":"REFERRED TO JUDICIARY","Date":"2019-03-13","Chamber":"SENATE"},
  {"Text":"REFERRED TO JUDICIARY","Date":"2020-01-08","Chamber":"SENATE"}
 ],
 "Sponsors":[{"ID":416,"Name":"Kevin S. Parker","Short":"PARKER"}],
 "Title":"Relates to the time to commence certain medical malpractice actions",
 "Summary":"Relates to the time to commence certain medical malpractice actions; provides that actions related to acts or omissions of hospitals where an incident report is required to be filed may be filed within one year of the required filing.",
 "LawSection":"Civil Practice Law and Rules",
 "LawCode":"Amd §214-a, CPLR; amd §2805-l, add §§2827 & 2828, Pub Health L",
 "ActClause":"AN ACT to amend the civil practice law and rules and the public health law, in relation to the time to commence certain malpractice actions",
 "PreviousVersions":["S5558-2009","S1098-2011","S2627-2013","S1209-2015","S3253-2017"]
}