{
 "PrintNo":"S5427","Session":2019,"Chamber":"SENATE","BillType":"Senate","Published":"2019-04-30T15:39:53.276073Z",
 "Status":"SENATE_FLOOR",
 "Milestones":[
  {"Type":"IN_SENATE_COMM","Date":"2019-04-30","Committee":"Commerce, Economic Development And Small Business"},
  {"Type":"SENATE_FLOOR","Date":"2019-06-03"}
 ],
 "Actions":[
  {"Text":"REFERRED TO COMMERCE, ECONOMIC DEVELOPMENT AND SMALL BUSINESS","Date":"2019-04-30","Chamber":"SENATE"},
  {"Text":"1ST REPORT CAL.957","Date":"2019-05-29","Chamber":"SENATE"},
  {"Text":"2ND REPORT CAL.","Date":"2019-05-30","Chamber":"SENATE"},
  {"Text":"ADVANCED TO THIRD READING","Date":"2019-06-03","Chamber":"SENATE"},
  {"Text":"SUBSTITUTED BY A1971","Date":"2019-06-14","Chamber":"SENATE"}
 ],
 "Votes":[
  {
   "VoteType":"COMMITTEE","Date":"2019-05-29","Chamber":"SENATE",
   "Committee":"Commerce, Economic Development And Small Business",
   "Votes":[
    {"ID":913,"Name":"Fredrick J. Akshar II","Short":"AKSHAR","Vote":"Aye"},
    {"ID":1102,"Name":"Jamaal Bailey","Short":"BAILEY","Vote":"Aye"},
    {"ID":433,"Name":"Phil Boyle","Short":"BOYLE","Vote":"Aye"},
    {"ID":1222,"Name":"Jim Gaughran","Short":"GAUGHRAN","Vote":"Aye"},
    {"ID":1233,"Name":"Pete Harckham","Short":"HARCKHAM","Vote":"Aye"},
    {"ID":951,"Name":"Pamela Helming","Short":"HELMING","Vote":"Aye"},
    {"ID":1224,"Name":"Anna Kaplan","Short":"KAPLAN","Vote":"Aye"},
    {"ID":914,"Name":"Roxanne J. Persaud","Short":"PERSAUD","Vote":"Aye"},
    {"ID":432,"Name":"James Sanders Jr.","Short":"SANDERS","Vote":"Aye"}
   ]
  }
 ],
 "Sponsors":[
  {"ID":1224,"Name":"Anna Kaplan","Short":"KAPLAN"},{"ID":379,"Name":"Betty Little","Short":"LITTLE"},
  {"ID":370,"Name":"David Carlucci","Short":"CARLUCCI"}
 ],
 "Title":"Expands the amount of barrels that a restaurant brewer may sell at retail",
 "Summary":"Expands the number of barrels that a restaurant brewer may sell at retail.",
 "LawSection":"Alcoholic Beverage Control Law","LawCode":"Amd ยง64-c, ABC L",
 "ActClause":"AN ACT to amend the alcoholic beverage control law, in relation to expanding the amount of barrels that a restaurant brewer may sell at retail",
 "SameAsPrintNo":"A1971-2019","PreviousVersions":["S5173-2017"]
}