{
 "PrintNo":"A3532","Version":"A","Session":2021,"Chamber":"ASSEMBLY","BillType":"Assembly",
 "Published":"2021-01-27T15:47:23.833943Z","Status":"IN_ASSEMBLY_COMM","Committee":"Transportation",
 "Milestones":[{"Type":"IN_ASSEMBLY_COMM","Date":"2022-01-05","Committee":"Transportation"}],
 "Actions":[
  {"Text":"REFERRED TO TRANSPORTATION","Date":"2021-01-27","Chamber":"ASSEMBLY"},
  {"Text":"AMEND AND RECOMMIT TO TRANSPORTATION","Date":"2021-04-15","Chamber":"ASSEMBLY"},
  {"Text":"PRINT NUMBER 3532A","Date":"2021-04-15","Chamber":"ASSEMBLY","Version":"A"},
  {"Text":"REFERRED TO TRANSPORTATION","Date":"2022-01-05","Chamber":"ASSEMBLY","Version":"A"},
  {"Text":"HELD FOR CONSIDERATION IN TRANSPORTATION","Date":"2022-04-25","Chamber":"ASSEMBLY","Version":"A"}
 ],
 "Votes":[
  {
   "VoteType":"Held for Consideration","Date":"1969-12-31","Chamber":"ASSEMBLY",
   "Votes":[
    {"ID":570,"Short":"MAGNARELLI","Vote":"Aye"},{"ID":576,"Short":"LUPARDO","Vote":"Aye"},
    {"ID":464,"Short":"THIELE","Vote":"Aye"},{"ID":633,"Short":"BRONSON","Vote":"Aye"},
    {"ID":907,"Short":"SIMON","Vote":"Aye"},{"ID":1105,"Short":"HUNTER","Vote":"Aye"},
    {"ID":1116,"Short":"WILLIAMS","Vote":"Aye"},{"ID":657,"Short":"FAHY","Vote":"Aye"},
    {"ID":1256,"Short":"FRONTUS","Vote":"Aye"},{"ID":1259,"Short":"JACOBSON","Vote":"Aye"},
    {"ID":1255,"Short":"MCMAHON","Vote":"Aye"},{"ID":1240,"Short":"DARLING","Vote":"Aye"},
    {"ID":1133,"Short":"WALLACE","Vote":"Aye"},{"ID":1463,"Short":"BURGOS","Vote":"Aye"},
    {"ID":1471,"Short":"GALLAGHER","Vote":"Aye"},{"ID":1472,"Short":"MITAYNES","Vote":"Aye"},
    {"ID":1467,"Short":"SILLITTI","Vote":"Aye"},{"ID":516,"Short":"CUSICK","Vote":"Aye"},
    {"ID":480,"Short":"MCDONOUGH","Vote":"Nay"},{"ID":656,"Short":"DIPIETRO","Vote":"Nay"},
    {"ID":1123,"Short":"BYRNE","Vote":"Nay"},{"ID":1125,"Short":"MILLER","Vote":"Nay"},
    {"ID":1126,"Short":"NORRIS","Vote":"Nay"},{"ID":1238,"Short":"DESTEFANO","Vote":"Nay"},
    {"ID":1247,"Short":"WALCZYK","Vote":"Nay"}
   ]
  }
 ],
 "Sponsors":[
  {"ID":1252,"Name":"Marjorie Byrnes","Short":"BYRNES"},{"ID":1238,"Name":"Joe DeStefano","Short":"DESTEFANO"},
  {"ID":1135,"Name":"Angelo J. Morinello","Short":"MORINELLO"},
  {"ID":476,"Name":"Michael Montesano","Short":"MONTESANO"}
 ],
 "Title":"Authorizes the village of Pittsford, town of Pittsford, Monroe county to lower the speed limit on state roads to not less than twenty-five miles per hour",
 "Summary":"Authorizes the village of Pittsford, town of Pittsford, Monroe county, to lower the speed limit on village roads to not less than twenty-five miles per hour.",
 "LawSection":"Vehicle and Traffic Law",
 "ActClause":"AN ACT relating to speed limits in the village of Pittsford, town of Pittsford, county of Monroe",
 "SameAsPrintNo":"S2959-2021","PreviousVersions":["A3794-2017","A4715-2019"]
}