{
 "PrintNo":"S2956","Session":2021,"Chamber":"SENATE","BillType":"Senate","Published":"2021-01-26T14:48:32.490396Z",
 "Status":"IN_SENATE_COMM","Committee":"Environmental Conservation",
 "Milestones":[{"Type":"IN_SENATE_COMM","Date":"2022-01-05","Committee":"Environmental Conservation"}],
 "Actions":[
  {"Text":"REFERRED TO ENVIRONMENTAL CONSERVATION","Date":"2021-01-26","Chamber":"SENATE"},
  {"Text":"REFERRED TO ENVIRONMENTAL CONSERVATION","Date":"2022-01-05","Chamber":"SENATE"}
 ],
 "Sponsors":[{"ID":1140,"Name":"Brian Kavanagh","Short":"KAVANAGH"}],
 "Title":"Prohibits the manufacture, distribution and sale of children's foam mats containing formamide",
 "Summary":"Prohibits the manufacture, distribution and sale of children's foam mats containing formamide.",
 "LawSection":"Environmental Conservation Law","LawCode":"Add Art 37 Title 4 §§37-0401 - 37-0409, En Con L",
 "ActClause":"AN ACT to amend the environmental conservation law, in relation to prohibiting the manufacture, distribution and sale of children's foam mats containing formamide",
 "PreviousVersions":["S7806-2013","S583-2015","S7089-2017","S2299-2019"]
}