{
 "PrintNo":"S3113","Session":2021,"Chamber":"SENATE","BillType":"Senate","Published":"2021-01-27T14:44:31.680907Z",
 "Status":"IN_SENATE_COMM","Committee":"Elections",
 "Milestones":[{"Type":"IN_SENATE_COMM","Date":"2022-01-05","Committee":"Elections"}],
 "Actions":[
  {"Text":"REFERRED TO ELECTIONS","Date":"2021-01-27","Chamber":"SENATE"},
  {"Text":"REFERRED TO ELECTIONS","Date":"2022-01-05","Chamber":"SENATE"}
 ],
 "Sponsors":[{"ID":401,"Name":"Liz Krueger","Short":"KRUEGER"},{"ID":373,"Name":"José M. Serrano","Short":"SERRANO"}],
 "Title":"Relates to increasing fines and penalties for certain violations; requires refund of certain illegal contributions",
 "Summary":"Relates to increasing fines and penalties for certain violations; requires refund of certain illegal contributions.",
 "LawSection":"Election Law","LawCode":"Amd §14-126, El L",
 "ActClause":"AN ACT to amend the election law, in relation to increasing penalties for certain violations",
 "PreviousVersions":["S4061-2009","S890-2011","S3273-2013","S2503-2015","S4232-2017","S3983-2019"]
}