{
 "PrintNo":"S4705","Session":2021,"Chamber":"SENATE","BillType":"Senate","Published":"2021-02-09T10:27:03.404052Z",
 "Status":"IN_SENATE_COMM","Committee":"Social Services",
 "Milestones":[{"Type":"IN_SENATE_COMM","Date":"2022-01-05","Committee":"Social Services"}],
 "Actions":[
  {"Text":"REFERRED TO SOCIAL SERVICES","Date":"2021-02-09","Chamber":"SENATE"},
  {"Text":"REFERRED TO SOCIAL SERVICES","Date":"2022-01-05","Chamber":"SENATE"}
 ],
 "Sponsors":[{"ID":918,"Name":"Todd Kaminsky","Short":"KAMINSKY"}],
 "Title":"Increases the standards of monthly need for eligible persons receiving enhanced residential care",
 "Summary":"Increases the standards of monthly need for eligible individuals and couples receiving enhanced residential care.",
 "LawSection":"Social Services Law","LawCode":"Amd ยง209, Soc Serv L",
 "ActClause":"AN ACT to amend the social services law, in relation to increasing the standards of monthly need for eligible persons receiving enhanced residential care"
}