{
 "PrintNo":"J420","Session":2025,"Chamber":"SENATE","BillType":"Regular and Joint","Resolution":true,
 "Published":"2025-02-26T11:46:40.063181Z","Status":"ADOPTED","Milestones":[{"Type":"ADOPTED","Date":"2025-03-04"}],
 "Actions":[
  {"Text":"REFERRED TO FINANCE","Date":"2025-02-26","Chamber":"SENATE"},
  {"Text":"REPORTED TO CALENDAR FOR CONSIDERATION","Date":"2025-03-04","Chamber":"SENATE"},
  {"Text":"ADOPTED","Date":"2025-03-04","Chamber":"SENATE"}
 ],
 "Sponsors":[{"ID":1499,"Name":"Peter Oberacker","Short":"OBERACKER"}],
 "Title":"Honoring the Oneonta High School Girls Track Team upon the occasion of their victory in the New York State Division II 4x100 Meter Relay at the 2024 New York State Track and Field Championships",
 "LawSection":"Resolutions, Legislative"
}