{
 "PrintNo":"A10392","Session":2023,"Chamber":"ASSEMBLY","BillType":"Assembly","Published":"2024-05-21T08:29:22.828306Z",
 "Status":"IN_ASSEMBLY_COMM","Committee":"Governmental Operations",
 "Milestones":[{"Type":"IN_ASSEMBLY_COMM","Date":"2024-05-21","Committee":"Governmental Operations"}],
 "Actions":[{"Text":"REFERRED TO GOVERNMENTAL OPERATIONS","Date":"2024-05-21","Chamber":"ASSEMBLY"}],
 "Sponsors":[{"ID":669,"Name":"Nily Rozic","Short":"ROZIC"},{"ID":1485,"Name":"Josh Jensen","Short":"JENSEN"}],
 "Title":"Prohibits sharing or selling personal data to third parties by government entities and contractors",
 "Summary":"Prohibits sharing or selling personal data to third parties by government entities and contractors.",
 "LawSection":"Executive Law","LawCode":"Add Art 5-A §§81 - 84, Exec L",
 "ActClause":"AN ACT to amend the executive law, in relation to prohibiting sharing or selling personal data to third parties by government entities and contractors"
}