{
 "PrintNo":"A3477","Session":2023,"Chamber":"ASSEMBLY","BillType":"Assembly","Published":"2023-02-03T11:34:57.528645Z",
 "Status":"IN_ASSEMBLY_COMM","Committee":"Transportation",
 "Milestones":[{"Type":"IN_ASSEMBLY_COMM","Date":"2024-01-03","Committee":"Transportation"}],
 "Actions":[
  {"Text":"REFERRED TO TRANSPORTATION","Date":"2023-02-03","Chamber":"ASSEMBLY"},
  {"Text":"HELD FOR CONSIDERATION IN TRANSPORTATION","Date":"2023-04-25","Chamber":"ASSEMBLY"},
  {"Text":"REFERRED TO TRANSPORTATION","Date":"2024-01-03","Chamber":"ASSEMBLY"}
 ],
 "Votes":[
  {
   "VoteType":"Held for Consideration","Date":"2023-04-25","Chamber":"ASSEMBLY","Committee":"TRANSPORTATION",
   "Votes":[
    {"ID":570,"Short":"MAGNARELLI","Vote":"Aye"},{"ID":576,"Short":"LUPARDO","Vote":"Aye"},
    {"ID":464,"Short":"THIELE","Vote":"Aye"},{"ID":907,"Short":"SIMON","Vote":"Aye"},
    {"ID":1116,"Short":"WILLIAMS","Vote":"Aye"},{"ID":657,"Short":"FAHY","Vote":"Aye"},
    {"ID":1255,"Short":"MCMAHON","Vote":"Aye"},{"ID":1240,"Short":"DARLING","Vote":"Aye"},
    {"ID":1133,"Short":"WALLACE","Vote":"Aye"},{"ID":1463,"Short":"BURGOS","Vote":"Aye"},
    {"ID":1471,"Short":"GALLAGHER","Vote":"Aye"},{"ID":1472,"Short":"MITAYNES","Vote":"Aye"},
    {"ID":1467,"Short":"SILLITTI","Vote":"Aye"},{"ID":1506,"Short":"DE LOS SANTOS","Vote":"Aye"},
    {"ID":1508,"Short":"CUNNINGHAM","Vote":"Aye"},{"ID":1533,"Short":"ALVAREZ","Vote":"Aye"},
    {"ID":1541,"Short":"SHRESTHA","Vote":"Aye"},{"ID":1535,"Short":"SHIMSKY","Vote":"Aye"},
    {"ID":1125,"Short":"MILLER","Vote":"Nay"},{"ID":1126,"Short":"NORRIS","Vote":"Nay"},
    {"ID":1238,"Short":"DESTEFANO","Vote":"Nay"},{"ID":1466,"Short":"DURSO","Vote":"Nay"},
    {"ID":0,"Short":"GIGLIO","Vote":"Nay"},{"ID":1538,"Short":"MCGOWAN","Vote":"Nay"},
    {"ID":1536,"Short":"SLATER","Vote":"Nay"},{"ID":480,"Short":"MCDONOUGH","Vote":"Excused"}
   ]
  }
 ],
 "Sponsors":[
  {"ID":1238,"Name":"Joe DeStefano","Short":"DESTEFANO"},{"ID":589,"Name":"Stephen Hawley","Short":"HAWLEY"},
  {"ID":1125,"Name":"Brian D. Miller","Short":"MILLER"},{"ID":480,"Name":"David McDonough","Short":"MCDONOUGH"},
  {"ID":1466,"Name":"Michael Durso","Short":"DURSO"},{"ID":1135,"Name":"Angelo J. Morinello","Short":"MORINELLO"},
  {"ID":1245,"Name":"Mike Reilly","Short":"REILLY"},{"ID":1509,"Name":"Eric Brown","Short":"BROWN E"},
  {"ID":1529,"Name":"Samuel Pirozzolo","Short":"PIROZZOLO"},{"ID":1543,"Name":"Scott H. Bendett","Short":"BENDETT"},
  {"ID":1481,"Name":"Joe Angelino","Short":"ANGELINO"},{"ID":1538,"Name":"John W. McGowan","Short":"MCGOWAN"}
 ],
 "Title":"Relates to criminal history background check of transportation network company drivers",
 "Summary":"Requires that a person shall be disqualified from receiving a transportation network company permit if he or she is convicted of a sex offense and such disqualification shall last the duration of time for which he or she is required to register as a sex offender.",
 "LawSection":"Vehicle and Traffic Law","LawCode":"Amd §§1699 & 1696, V & T L",
 "ActClause":"AN ACT to amend the vehicle and traffic law, in relation to criminal history background check of transportation network company drivers",
 "PreviousVersions":["A7753-2017","A6103-2019","A3893-2021"]
}