{
 "PrintNo":"A7023","Version":"A","Session":2023,"Chamber":"ASSEMBLY","BillType":"Assembly",
 "Published":"2023-05-10T09:34:21.138443Z","Status":"IN_ASSEMBLY_COMM","Committee":"Governmental Employees",
 "Milestones":[{"Type":"IN_ASSEMBLY_COMM","Date":"2024-03-04","Committee":"Governmental Employees"}],
 "Actions":[
  {"Text":"REFERRED TO GOVERNMENTAL EMPLOYEES","Date":"2023-05-10","Chamber":"ASSEMBLY"},
  {"Text":"REFERRED TO GOVERNMENTAL EMPLOYEES","Date":"2024-01-03","Chamber":"ASSEMBLY"},
  {"Text":"AMEND AND RECOMMIT TO GOVERNMENTAL EMPLOYEES","Date":"2024-03-04","Chamber":"ASSEMBLY"},
  {"Text":"PRINT NUMBER 7023A","Date":"2024-03-04","Chamber":"ASSEMBLY","Version":"A"}
 ],
 "Sponsors":[
  {"ID":1131,"Name":"Stacey Pheffer Amato","Short":"PHEFFER AMATO"},{"ID":1482,"Name":"Anna Kelles","Short":"KELLES"},
  {"ID":1537,"Name":"Dana Levenberg","Short":"LEVENBERG"},{"ID":464,"Name":"Fred Thiele","Short":"THIELE"},
  {"ID":1465,"Name":"Jerett Gandolfo","Short":"GANDOLFO"},{"ID":1478,"Name":"Chris Burdick","Short":"BURDICK"},
  {"ID":1487,"Name":"William Conrad","Short":"CONRAD"},{"ID":1255,"Name":"Karen McMahon","Short":"MCMAHON"},
  {"ID":1481,"Name":"Joe Angelino","Short":"ANGELINO"},{"ID":1238,"Name":"Joe DeStefano","Short":"DESTEFANO"}
 ],
 "Title":"Relates to increasing the base benefit amount for computation of pension cost-of-living adjustments",
 "Summary":"Increases the base benefit amount for computation of pension cost-of-living adjustments.",
 "LawSection":"Retirement and Social Security Law","LawCode":"Amd §§78-a & 378-a, R & SS L; amd §532-a, Ed L",
 "ActClause":"AN ACT to amend the retirement and social security law and the education law, in relation to increasing the base benefit amount for computation of pension cost-of-living adjustments",
 "SameAsPrintNo":"S6307-2023","PreviousVersions":["S6835-2021"]
}