{
 "PrintNo":"K169","Session":2023,"Chamber":"ASSEMBLY","BillType":"Regular","Resolution":true,
 "Published":"2023-03-08T16:31:51.147814Z","Status":"ADOPTED","Milestones":[{"Type":"ADOPTED","Date":"2023-03-09"}],
 "Actions":[
  {"Text":"INTRODUCED","Date":"2023-03-08","Chamber":"ASSEMBLY"},
  {"Text":"ADOPTED","Date":"2023-03-09","Chamber":"ASSEMBLY"}
 ],
 "Sponsors":[{"ID":1484,"Name":"Jeff Gallahan","Short":"GALLAHAN"}],
 "Title":"Congratulating Sophie Pollack upon the occasion of capturing the 185-pound Division wrestling title at the first ever NYSPHSAA Girls State Wrestling Invitational",
 "LawSection":"Resolutions, Legislative"
}