{
 "PrintNo":"K597","Session":2023,"Chamber":"ASSEMBLY","BillType":"Regular","Resolution":true,
 "Published":"2023-05-31T18:50:31.404668Z","Status":"ADOPTED","Milestones":[{"Type":"ADOPTED","Date":"2023-06-01"}],
 "Actions":[
  {"Text":"REFERRED TO CALENDAR","Date":"2023-05-31","Chamber":"ASSEMBLY"},
  {"Text":"ADOPTED","Date":"2023-06-01","Chamber":"ASSEMBLY"}
 ],
 "Sponsors":[
  {"ID":1116,"Name":"Jaime R. Williams","Short":"WILLIAMS"},{"ID":625,"Name":"Didi Barrett","Short":"BARRETT"},
  {"ID":1542,"Name":"Anil Beephan Jr.","Short":"BEEPHAN"},{"ID":1509,"Name":"Eric Brown","Short":"BROWN E"},
  {"ID":1249,"Name":"Marianne Buttenschon","Short":"BUTTENSCHON"},{"ID":500,"Name":"William Colton","Short":"COLTON"},
  {"ID":1508,"Name":"Brian Cunningham","Short":"CUNNINGHAM"},{"ID":607,"Name":"Brian F. Curran","Short":"CURRAN"},
  {"ID":1238,"Name":"Joe DeStefano","Short":"DESTEFANO"},{"ID":599,"Name":"Joseph Giglio","Short":"GIGLIO JM"},
  {"ID":519,"Name":"Deborah Glick","Short":"GLICK"},
  {"ID":1468,"Name":"Jessica Gonzalez-Rojas","Short":"GONZALEZ-ROJAS"},
  {"ID":549,"Name":"Aileen Gunther","Short":"GUNTHER"},{"ID":1120,"Name":"Billy Jones","Short":"JONES"},
  {"ID":576,"Name":"Donna Lupardo","Short":"LUPARDO"},{"ID":1540,"Name":"Brian Maher","Short":"MAHER"},
  {"ID":662,"Name":"John T. McDonald III","Short":"MCDONALD"},{"ID":1150,"Name":"John K. Mikulin","Short":"MIKULIN"},
  {"ID":1125,"Name":"Brian D. Miller","Short":"MILLER"},{"ID":1527,"Name":"Michael Novakhov","Short":"NOVAKHOV"},
  {"ID":1525,"Name":"Steven Raga","Short":"RAGA"},{"ID":468,"Name":"Philip Ramos","Short":"RAMOS"},
  {"ID":669,"Name":"Nily Rozic","Short":"ROZIC"},{"ID":1467,"Name":"Gina Sillitti","Short":"SILLITTI"},
  {"ID":907,"Name":"Jo Anne Simon","Short":"SIMON"},{"ID":1532,"Name":"Tony Simone","Short":"SIMONE"},
  {"ID":1152,"Name":"Chris Tague","Short":"TAGUE"},{"ID":545,"Name":"Kenneth Zebrowski","Short":"ZEBROWSKI"}
 ],
 "Title":"Memorializing Governor Kathy Hochul to proclaim June 2023, as Caribbean Heritage Month in the State of New York",
 "LawSection":"Resolutions, Legislative"
}